MANIFEST.in
README.rst
setup.py
cubemx2cmake/__init__.py
cubemx2cmake/command_line.py
cubemx2cmake.egg-info/PKG-INFO
cubemx2cmake.egg-info/SOURCES.txt
cubemx2cmake.egg-info/dependency_links.txt
cubemx2cmake.egg-info/entry_points.txt
cubemx2cmake.egg-info/not-zip-safe
cubemx2cmake.egg-info/top_level.txt
cubemx2cmake/templates/CMakeLists.txt.template
cubemx2cmake/templates/STM32Toolchain.cmake.template
cubemx2cmake/templates/gdb.sh.template
cubemx2cmake/templates/openocd_debug.cfg.template
cubemx2cmake/templates/openocd_debug.sh.template
cubemx2cmake/templates/openocd_flash.cfg.template
cubemx2cmake/templates/openocd_flash.sh.template