Metadata-Version: 1.1
Name: cubemx2cmake
Version: 1.2
Summary: Command line tool to generate CMakeLists.txt from STM32CubeMX projects.
Home-page: https://github.com/eugene-babichenko/cubemx2cmake
Author: Yevhenii Babichenko
Author-email: eugene.babichenko@gmail.com
License: MIT
Keywords: st stm32 cube cubemx stm32cubemx cmake code generator
Platform: UNKNOWN
Classifier: Topic :: Software Development :: Code Generators
Classifier: Topic :: Utilities
